datels/__init__.py
datels/cli.py
datels/datels.py
datels-1.0.1.dist-info/entry_points.txt
datels-1.0.1.dist-info/LICENSE
datels-1.0.1.dist-info/WHEEL
datels-1.0.1.dist-info/METADATA
datels-1.0.1.dist-info/RECORD
