Metadata-Version: 2.1
Name: datels
Version: 1.0.1
Summary: `datels` is a simple CLI that displays a list of dates line by line.
Home-page: https://github.com/joe-yama/datels
License: MIT
Author: joe-yama
Author-email: s1r0mqme@gmail.com
Requires-Python: >=3.7,<3.10
Classifier: License :: OSI Approved :: MIT License
Classifier: Programming Language :: Python :: 3
Classifier: Programming Language :: Python :: 3.7
Classifier: Programming Language :: Python :: 3.8
Classifier: Programming Language :: Python :: 3.9
Requires-Dist: fire (>=0.4.0,<0.5.0)
Requires-Dist: numpy (>=1.21)
Project-URL: Repository, https://github.com/joe-yama/datels
